dovpanda/__init__.py
dovpanda_by_guy-0.0.4.dist-info/LICENSE
dovpanda_by_guy-0.0.4.dist-info/METADATA
dovpanda_by_guy-0.0.4.dist-info/WHEEL
dovpanda_by_guy-0.0.4.dist-info/top_level.txt
dovpanda_by_guy-0.0.4.dist-info/RECORD
