Metadata-Version: 2.1
Name: dovpanda-by-guy
Version: 0.0.4
Summary: Directions overlay for working with pandas in an analysis environment
Home-page: https://github.com/guysmoilov/dovpanda
Author: guysmoilov
License: UNKNOWN
Platform: UNKNOWN
Classifier: Programming Language :: Python :: 3
Classifier: License :: OSI Approved :: BSD License
Classifier: Operating System :: OS Independent
Requires-Python: >=3.6
